django_q_rollbar/__init__.py
django_q_rollbar/rollbar.py
django_q_rollbar-0.1.1.dist-info/DESCRIPTION.rst
django_q_rollbar-0.1.1.dist-info/METADATA
django_q_rollbar-0.1.1.dist-info/RECORD
django_q_rollbar-0.1.1.dist-info/WHEEL
django_q_rollbar-0.1.1.dist-info/metadata.json
django_q_rollbar-0.1.1.dist-info/top_level.txt
