Metadata-Version: 2.0
Name: django-q-rollbar
Version: 0.1.1
Summary: A Rollbar support plugin for Django Q
Home-page: https://django-q.readthedocs.org
Author: Daniel Welch
Author-email: dwelch2102@gmail.com
License: MIT
Keywords: django distributed task queue worker scheduler cron redis disque ironmq sqs orm mongodb multiprocessing rollbar
Platform: UNKNOWN
